{
    "homepage": "https://gh.lacymorrow.com/crossover/",
    "description": "🎯 A Crosshair Overlay for any screen.",
    "license": "CC-BY-NC-SA-4.0",
    "version": "3.3.4",
    "url": "https://github.com/lacymorrow/crossover/releases/download/v3.3.4/CrossOver-Portable-3.3.4.exe#/CrossOver-Portable.exe",
    "hash": "ec8413652e57b500bc75b79b66986d75df0fd3244848e24261f4a9293d8216b0",
    "shortcuts": [
        [
            "CrossOver-Portable.exe",
            "CrossOver"
        ]
    ],
    "checkver": {
        "github": "https://github.com/lacymorrow/crossover"
    },
    "autoupdate": {
        "url": "https://github.com/lacymorrow/crossover/releases/download/v$version/CrossOver-Portable-$version.exe#/CrossOver-Portable.exe"
    }
}
