{
    "homepage": "https://houdoku.org/",
    "description": "Manga reader and library manager for the desktop",
    "license": "MIT",
    "version": "2.4.0",
    "url": "https://github.com/xgi/houdoku/releases/download/v2.4.0/Houdoku-Setup-2.4.0.exe#/dl.7z",
    "hash": "7ebbe4786c61902077e8189e2d9e93afc7445abf99303b7a7d075b4813502474",
    "shortcuts": [
        [
            "Houdoku.exe",
            "Houdoku"
        ]
    ],
    "checkver": {
        "github": "https://github.com/xgi/houdoku"
    },
    "autoupdate": {
        "url": "https://github.com/xgi/houdoku/releases/download/v$version/Houdoku-Setup-$version.exe#/dl.7z"
    }
}
