{
    "homepage": "https://luau-lang.org/",
    "description": "A fast, small, safe, gradually typed embeddable scripting language derived from Lua",
    "license": "MIT",
    "version": "0.516",
    "url": "https://github.com/Roblox/luau/releases/download/0.516/luau-windows.zip",
    "hash": "8b5736e1ba79626d6ce1f7de0151c767c9cf6eba8c25a946f4be2f846417f2f6",
    "bin": [
        "luau.exe",
        "luau-analyze.exe"
    ],
    "checkver": {
        "github": "https://github.com/Roblox/luau"
    },
    "autoupdate": {
        "url": "https://github.com/Roblox/luau/releases/download/$version/luau-windows.zip"
    }
}
