{
    "homepage": "https://luau-lang.org/",
    "description": "A fast, small, safe, gradually typed embeddable scripting language derived from Lua",
    "license": "MIT",
    "version": "0.518",
    "url": "https://github.com/Roblox/luau/releases/download/0.518/luau-windows.zip",
    "hash": "3b5855546b6adeec744b14ca65d04f40bd3ae7c751a524c26092a2d1dad8f578",
    "bin": [
        "luau.exe",
        "luau-analyze.exe"
    ],
    "checkver": {
        "github": "https://github.com/Roblox/luau"
    },
    "autoupdate": {
        "url": "https://github.com/Roblox/luau/releases/download/$version/luau-windows.zip"
    }
}
