{
    "homepage": "https://www.ponylang.io/",
    "description": "Open-source, actor-model, capabilities-secure, high performance programming language",
    "license": "BSD-2-Clause",
    "version": "0.49.0",
    "architecture": {
        "64bit": {
            "url": "https://dl.cloudsmith.io/public/ponylang/releases/raw/versions/0.49.0/ponyc-x86-64-pc-windows-msvc.zip",
            "hash": "b0d425c07440dc7f9f9e1190876dedc6d2928c60c194276ee92562d362b8b798"
        }
    },
    "bin": "bin\\ponyc.exe",
    "checkver": {
        "github": "https://github.com/ponylang/ponyc"
    },
    "autoupdate": {
        "architecture": {
            "64bit": {
                "url": "https://dl.cloudsmith.io/public/ponylang/releases/raw/versions/$version/ponyc-x86-64-pc-windows-msvc.zip"
            }
        }
    }
}
