{
    "version": "1.8.5",
    "description": "A flexible level editor",
    "homepage": "https://www.mapeditor.org/",
    "license": {
        "identifier": "GPL-2.0-only",
        "url": "https://github.com/mapeditor/tiled/blob/master/COPYING"
    },
    "architecture": {
        "64bit": {
            "url": "https://github.com/mapeditor/tiled/releases/download/v1.8.5/Tiled-1.8.5-win64.msi",
            "hash": "141b8ef00987aa4ff85f71281d1afbafd06b33baed212ea99bb3ef514806ab8a"
        },
        "32bit": {
            "url": "https://github.com/mapeditor/tiled/releases/download/v1.8.5/Tiled-1.8.5-win32.msi",
            "hash": "af2ccb1b075cb9ba6e80125f8b5d82552ec5bbdc5a565bef2403eb38e12dde83"
        }
    },
    "extract_dir": "PFiles\\Tiled",
    "bin": "tiled.exe",
    "shortcuts": [
        [
            "tiled.exe",
            "Tiled"
        ]
    ],
    "checkver": {
        "github": "https://github.com/mapeditor/tiled"
    },
    "autoupdate": {
        "architecture": {
            "64bit": {
                "url": "https://github.com/mapeditor/tiled/releases/download/v$version/Tiled-$version-win64.msi"
            },
            "32bit": {
                "url": "https://github.com/mapeditor/tiled/releases/download/v$version/Tiled-$version-win32.msi"
            }
        }
    }
}
